odoo/addons/maintenance_equipment_always_fold/README.rst
odoo/addons/maintenance_equipment_always_fold/__init__.py
odoo/addons/maintenance_equipment_always_fold/__manifest__.py
odoo/addons/maintenance_equipment_always_fold/demo/maintenance_demo.xml
odoo/addons/maintenance_equipment_always_fold/i18n/es.po
odoo/addons/maintenance_equipment_always_fold/i18n/it.po
odoo/addons/maintenance_equipment_always_fold/i18n/maintenance_equipment_always_fold.pot
odoo/addons/maintenance_equipment_always_fold/i18n/pt_BR.po
odoo/addons/maintenance_equipment_always_fold/models/__init__.py
odoo/addons/maintenance_equipment_always_fold/models/maintenance.py
odoo/addons/maintenance_equipment_always_fold/readme/CONTRIBUTORS.rst
odoo/addons/maintenance_equipment_always_fold/readme/DESCRIPTION.rst
odoo/addons/maintenance_equipment_always_fold/static/description/icon.png
odoo/addons/maintenance_equipment_always_fold/static/description/index.html
odoo/addons/maintenance_equipment_always_fold/tests/__init__.py
odoo/addons/maintenance_equipment_always_fold/tests/test_maintenance_equipment_always_fold.py
odoo/addons/maintenance_equipment_always_fold/views/maintenance_views.xml
odoo13_addon_maintenance_equipment_always_fold-13.0.1.0.1.dev5.dist-info/METADATA
odoo13_addon_maintenance_equipment_always_fold-13.0.1.0.1.dev5.dist-info/WHEEL
odoo13_addon_maintenance_equipment_always_fold-13.0.1.0.1.dev5.dist-info/top_level.txt
odoo13_addon_maintenance_equipment_always_fold-13.0.1.0.1.dev5.dist-info/RECORD
