Metadata-Version: 2.1
Name: odoo13-addon-maintenance-equipment-always-fold
Version: 13.0.1.0.1.dev5
Summary: Equipment categories will always be folded if I indicate it with an always_fold Boolean; if not, let him behave as before
Home-page: https://github.com/OCA/maintenance
Author: Odoo Community Association (OCA), Solvos
Author-email: support@odoo-community.org
License: AGPL-3
Platform: UNKNOWN
Classifier: Programming Language :: Python
Classifier: Framework :: Odoo
Classifier: Framework :: Odoo :: 13.0
Classifier: License :: OSI Approved :: GNU Affero General Public License v3
Requires-Python: >=3.5
Requires-Dist: odoo <13.1dev,>=13.0a
